MANIFEST.in
README.md
odbc-cli
setup.py
odbcli/__init__.py
odbcli/__main__.py
odbcli/app.py
odbcli/cli.py
odbcli/config.py
odbcli/conn.py
odbcli/dbmetadata.py
odbcli/disconnect_dialog.py
odbcli/filters.py
odbcli/layout.py
odbcli/loginprompt.py
odbcli/odbclirc
odbcli/odbcstyle.py
odbcli/preview.py
odbcli/sidebar.py
odbcli/utils.py
odbcli.egg-info/PKG-INFO
odbcli.egg-info/SOURCES.txt
odbcli.egg-info/dependency_links.txt
odbcli.egg-info/requires.txt
odbcli.egg-info/top_level.txt
odbcli/completion/__init__.py
odbcli/completion/mssqlcompleter.py
odbcli/completion/prioritization.py
odbcli/completion/sqlcompletion.py
odbcli/completion/mssqlliterals/__init__.py
odbcli/completion/mssqlliterals/main.py
odbcli/completion/mssqlliterals/sqlliterals.json
odbcli/completion/parseutils/__init__.py
odbcli/completion/parseutils/ctes.py
odbcli/completion/parseutils/meta.py
odbcli/completion/parseutils/tables.py
odbcli/completion/parseutils/utils.py