Metadata-Version: 2.1
Name: odbcli
Version: 0.0.5
Summary: ODBC Client
Home-page: https://github.com/pypa/odbc-cli
Author: Oliver Gjoneski
Author-email: ogjoneski@gmail.com
License: BSD-3
Platform: UNKNOWN
Classifier: Programming Language :: Python :: 3
Classifier: License :: OSI Approved :: BSD License
Classifier: Operating System :: OS Independent
Requires-Python: >=3.6.1
